LICENSE
MANIFEST.in
README.md
requirements.txt
setup.py
bin/buli
bundesliga/__init__.py
bundesliga/cli.py
bundesliga/helpers.py
bundesliga/openligadb.py
bundesliga_cli.egg-info/PKG-INFO
bundesliga_cli.egg-info/SOURCES.txt
bundesliga_cli.egg-info/dependency_links.txt
bundesliga_cli.egg-info/requires.txt
bundesliga_cli.egg-info/top_level.txt