Metadata-Version: 1.0
Name: bundesliga-cli
Version: 0.2.0
Summary: Bundesliga results and stats for hackers
Home-page: https://github.com/hypebeast/bundesliga-cli
Author: Sebastian Ruml
Author-email: sebastian@sebastianruml.name
License: The MIT License (MIT)
